{
  "lastUpdated": "2025-12-09T07:24:34.455Z",
  "summary": {
    "totalPrizeDistributed": 22997,
    "totalPaid": 21997,
    "totalPending": 1000,
    "gameweekPrizes": 14999,
    "monthlyPrizes": 7998,
    "completedGameweeks": 15,
    "completedMonths": 4,
    "totalWinners": 54,
    "lastProcessedGW": 15
  },
  "winners": [
    {
      "playerName": "Bhushan Wagh",
      "totalPrizeWon": 2350,
      "totalPaid": 2350,
      "totalPending": 0,
      "prizeBreakdown": {
        "gameweek": 1650,
        "monthly": 700
      },
      "highlights": {
        "gameWeeks": 3,
        "gameMonths": 1,
        "overallRank": 20,
        "totalPoints": 843,
        "currentGWPoints": 54,
        "previousRank": 19,
        "deficitFromLeader": 82
      },
      "achievements": {
        "gameweeks": [
          {
            "week": 3,
            "position": "2nd",
            "prize": 350,
            "status": "Paid"
          },
          {
            "week": 4,
            "position": "1st",
            "prize": 650,
            "status": "Paid"
          },
          {
            "week": 5,
            "position": "1st",
            "prize": 650,
            "status": "Paid"
          }
        ],
        "months": [
          {
            "month": 2,
            "position": "2nd",
            "prize": 700,
            "status": "Paid"
          }
        ]
      },
      "positions": {
        "first": 2,
        "second": 2
      },
      "totalPoints": 843,
      "movement": {
        "direction": "down",
        "change": 1,
        "icon": "⬇",
        "displayText": "-1"
      }
    },
    {
      "playerName": "Vinay Sudershan",
      "totalPrizeWon": 2300,
      "totalPaid": 2300,
      "totalPending": 0,
      "prizeBreakdown": {
        "gameweek": 1000,
        "monthly": 1300
      },
      "highlights": {
        "gameWeeks": 2,
        "gameMonths": 1,
        "overallRank": 36,
        "totalPoints": 794,
        "currentGWPoints": 49,
        "previousRank": 34,
        "deficitFromLeader": 131
      },
      "achievements": {
        "gameweeks": [
          {
            "week": 8,
            "position": "2nd",
            "prize": 350,
            "status": "Paid"
          },
          {
            "week": 9,
            "position": "1st",
            "prize": 650,
            "status": "Paid"
          }
        ],
        "months": [
          {
            "month": 3,
            "position": "1st",
            "prize": 1300,
            "status": "Paid"
          }
        ]
      },
      "positions": {
        "first": 2,
        "second": 1
      },
      "totalPoints": 794,
      "movement": {
        "direction": "down",
        "change": 2,
        "icon": "⬇",
        "displayText": "-2"
      }
    },
    {
      "playerName": "Shubham Tripathi",
      "totalPrizeWon": 1950,
      "totalPaid": 1950,
      "totalPending": 0,
      "prizeBreakdown": {
        "gameweek": 650,
        "monthly": 1300
      },
      "highlights": {
        "gameWeeks": 1,
        "gameMonths": 1,
        "overallRank": 3,
        "totalPoints": 904,
        "currentGWPoints": 44,
        "previousRank": 1,
        "deficitFromLeader": 21
      },
      "achievements": {
        "gameweeks": [
          {
            "week": 6,
            "position": "1st",
            "prize": 650,
            "status": "Paid"
          }
        ],
        "months": [
          {
            "month": 2,
            "position": "1st",
            "prize": 1300,
            "status": "Paid"
          }
        ]
      },
      "positions": {
        "first": 2,
        "second": 0
      },
      "totalPoints": 904,
      "movement": {
        "direction": "down",
        "change": 2,
        "icon": "⬇",
        "displayText": "-2"
      }
    },
    {
      "playerName": "Siddharth Sharma",
      "totalPrizeWon": 1800,
      "totalPaid": 1800,
      "totalPending": 0,
      "prizeBreakdown": {
        "gameweek": 500,
        "monthly": 1300
      },
      "highlights": {
        "gameWeeks": 1,
        "gameMonths": 1,
        "overallRank": 4,
        "totalPoints": 899,
        "currentGWPoints": 58,
        "previousRank": 4,
        "deficitFromLeader": 26
      },
      "achievements": {
        "gameweeks": [
          {
            "week": 13,
            "position": "1st",
            "prize": 500,
            "status": "Paid"
          }
        ],
        "months": [
          {
            "month": 4,
            "position": "1st",
            "prize": 1300,
            "status": "Paid"
          }
        ]
      },
      "positions": {
        "first": 2,
        "second": 0
      },
      "totalPoints": 899,
      "movement": {
        "direction": "same",
        "change": 0,
        "icon": "⚬",
        "displayText": "—"
      }
    },
    {
      "playerName": "Siddharth Krishna",
      "totalPrizeWon": 1350,
      "totalPaid": 1350,
      "totalPending": 0,
      "prizeBreakdown": {
        "gameweek": 650,
        "monthly": 700
      },
      "highlights": {
        "gameWeeks": 1,
        "gameMonths": 1,
        "overallRank": 18,
        "totalPoints": 847,
        "currentGWPoints": 46,
        "previousRank": 14,
        "deficitFromLeader": 78
      },
      "achievements": {
        "gameweeks": [
          {
            "week": 8,
            "position": "1st",
            "prize": 650,
            "status": "Paid"
          }
        ],
        "months": [
          {
            "month": 3,
            "position": "2nd",
            "prize": 700,
            "status": "Paid"
          }
        ]
      },
      "positions": {
        "first": 1,
        "second": 1
      },
      "totalPoints": 847,
      "movement": {
        "direction": "down",
        "change": 4,
        "icon": "⬇",
        "displayText": "-4"
      }
    },
    {
      "playerName": "Kiran Kanoj",
      "totalPrizeWon": 1316,
      "totalPaid": 1316,
      "totalPending": 0,
      "prizeBreakdown": {
        "gameweek": 650,
        "monthly": 666
      },
      "highlights": {
        "gameWeeks": 1,
        "gameMonths": 1,
        "overallRank": 2,
        "totalPoints": 915,
        "currentGWPoints": 67,
        "previousRank": 3,
        "deficitFromLeader": 10
      },
      "achievements": {
        "gameweeks": [
          {
            "week": 2,
            "position": "1st",
            "prize": 650,
            "status": "Paid"
          }
        ],
        "months": [
          {
            "month": 1,
            "position": "1st",
            "prize": 666,
            "status": "Paid"
          }
        ]
      },
      "positions": {
        "first": 2,
        "second": 0
      },
      "totalPoints": 915,
      "movement": {
        "direction": "up",
        "change": 1,
        "icon": "⬆",
        "displayText": "+1"
      }
    },
    {
      "playerName": "Avanit Kaushal",
      "totalPrizeWon": 1316,
      "totalPaid": 1316,
      "totalPending": 0,
      "prizeBreakdown": {
        "gameweek": 650,
        "monthly": 666
      },
      "highlights": {
        "gameWeeks": 1,
        "gameMonths": 1,
        "overallRank": 10,
        "totalPoints": 871,
        "currentGWPoints": 37,
        "previousRank": 5,
        "deficitFromLeader": 54
      },
      "achievements": {
        "gameweeks": [
          {
            "week": 1,
            "position": "1st",
            "prize": 650,
            "status": "Paid"
          }
        ],
        "months": [
          {
            "month": 1,
            "position": "1st",
            "prize": 666,
            "status": "Paid"
          }
        ]
      },
      "positions": {
        "first": 2,
        "second": 0
      },
      "totalPoints": 871,
      "movement": {
        "direction": "down",
        "change": 5,
        "icon": "⬇",
        "displayText": "-5"
      }
    },
    {
      "playerName": "Lakshman Aravind ",
      "totalPrizeWon": 1000,
      "totalPaid": 1000,
      "totalPending": 0,
      "prizeBreakdown": {
        "gameweek": 1000,
        "monthly": 0
      },
      "highlights": {
        "gameWeeks": 2,
        "gameMonths": 0,
        "overallRank": 9,
        "totalPoints": 873,
        "currentGWPoints": 46,
        "previousRank": 8,
        "deficitFromLeader": 52
      },
      "achievements": {
        "gameweeks": [
          {
            "week": 3,
            "position": "1st",
            "prize": 650,
            "status": "Paid"
          },
          {
            "week": 6,
            "position": "2nd",
            "prize": 350,
            "status": "Paid"
          }
        ],
        "months": []
      },
      "positions": {
        "first": 1,
        "second": 1
      },
      "totalPoints": 873,
      "movement": {
        "direction": "down",
        "change": 1,
        "icon": "⬇",
        "displayText": "-1"
      }
    },
    {
      "playerName": "Alen Aloysius",
      "totalPrizeWon": 700,
      "totalPaid": 700,
      "totalPending": 0,
      "prizeBreakdown": {
        "gameweek": 0,
        "monthly": 700
      },
      "highlights": {
        "gameWeeks": 0,
        "gameMonths": 1,
        "overallRank": 8,
        "totalPoints": 876,
        "currentGWPoints": 50,
        "previousRank": 9,
        "deficitFromLeader": 49
      },
      "achievements": {
        "gameweeks": [],
        "months": [
          {
            "month": 4,
            "position": "2nd",
            "prize": 700,
            "status": "Paid"
          }
        ]
      },
      "positions": {
        "first": 0,
        "second": 1
      },
      "totalPoints": 876,
      "movement": {
        "direction": "up",
        "change": 1,
        "icon": "⬆",
        "displayText": "+1"
      }
    },
    {
      "playerName": "Sidharthshankar Pati",
      "totalPrizeWon": 683,
      "totalPaid": 683,
      "totalPending": 0,
      "prizeBreakdown": {
        "gameweek": 683,
        "monthly": 0
      },
      "highlights": {
        "gameWeeks": 2,
        "gameMonths": 0,
        "overallRank": 32,
        "totalPoints": 808,
        "currentGWPoints": 59,
        "previousRank": 33,
        "deficitFromLeader": 117
      },
      "achievements": {
        "gameweeks": [
          {
            "week": 1,
            "position": "2nd",
            "prize": 350,
            "status": "Paid"
          },
          {
            "week": 14,
            "position": "1st",
            "prize": 333,
            "status": "Paid"
          }
        ],
        "months": []
      },
      "positions": {
        "first": 1,
        "second": 1
      },
      "totalPoints": 808,
      "movement": {
        "direction": "up",
        "change": 1,
        "icon": "⬆",
        "displayText": "+1"
      }
    },
    {
      "playerName": "B V Dhananjay",
      "totalPrizeWon": 666,
      "totalPaid": 666,
      "totalPending": 0,
      "prizeBreakdown": {
        "gameweek": 0,
        "monthly": 666
      },
      "highlights": {
        "gameWeeks": 0,
        "gameMonths": 1,
        "overallRank": 1,
        "totalPoints": 925,
        "currentGWPoints": 70,
        "previousRank": 2,
        "deficitFromLeader": 0
      },
      "achievements": {
        "gameweeks": [],
        "months": [
          {
            "month": 1,
            "position": "1st",
            "prize": 666,
            "status": "Paid"
          }
        ]
      },
      "positions": {
        "first": 1,
        "second": 0
      },
      "totalPoints": 925,
      "movement": {
        "direction": "up",
        "change": 1,
        "icon": "⬆",
        "displayText": "+1"
      }
    },
    {
      "playerName": "Sourabh Mandal",
      "totalPrizeWon": 650,
      "totalPaid": 650,
      "totalPending": 0,
      "prizeBreakdown": {
        "gameweek": 650,
        "monthly": 0
      },
      "highlights": {
        "gameWeeks": 1,
        "gameMonths": 0,
        "overallRank": 31,
        "totalPoints": 809,
        "currentGWPoints": 54,
        "previousRank": 32,
        "deficitFromLeader": 116
      },
      "achievements": {
        "gameweeks": [
          {
            "week": 10,
            "position": "1st",
            "prize": 650,
            "status": "Paid"
          }
        ],
        "months": []
      },
      "positions": {
        "first": 1,
        "second": 0
      },
      "totalPoints": 809,
      "movement": {
        "direction": "up",
        "change": 1,
        "icon": "⬆",
        "displayText": "+1"
      }
    },
    {
      "playerName": "Raghav Verma",
      "totalPrizeWon": 650,
      "totalPaid": 650,
      "totalPending": 0,
      "prizeBreakdown": {
        "gameweek": 650,
        "monthly": 0
      },
      "highlights": {
        "gameWeeks": 1,
        "gameMonths": 0,
        "overallRank": 53,
        "totalPoints": 668,
        "currentGWPoints": 54,
        "previousRank": 53,
        "deficitFromLeader": 257
      },
      "achievements": {
        "gameweeks": [
          {
            "week": 11,
            "position": "1st",
            "prize": 650,
            "status": "Paid"
          }
        ],
        "months": []
      },
      "positions": {
        "first": 1,
        "second": 0
      },
      "totalPoints": 668,
      "movement": {
        "direction": "same",
        "change": 0,
        "icon": "⚬",
        "displayText": "—"
      }
    },
    {
      "playerName": "Tulasi Ram Garapati",
      "totalPrizeWon": 650,
      "totalPaid": 650,
      "totalPending": 0,
      "prizeBreakdown": {
        "gameweek": 650,
        "monthly": 0
      },
      "highlights": {
        "gameWeeks": 1,
        "gameMonths": 0,
        "overallRank": 50,
        "totalPoints": 726,
        "currentGWPoints": 46,
        "previousRank": 50,
        "deficitFromLeader": 199
      },
      "achievements": {
        "gameweeks": [
          {
            "week": 12,
            "position": "1st",
            "prize": 650,
            "status": "Paid"
          }
        ],
        "months": []
      },
      "positions": {
        "first": 1,
        "second": 0
      },
      "totalPoints": 726,
      "movement": {
        "direction": "same",
        "change": 0,
        "icon": "⚬",
        "displayText": "—"
      }
    },
    {
      "playerName": "Arkadeep Bal",
      "totalPrizeWon": 650,
      "totalPaid": 650,
      "totalPending": 0,
      "prizeBreakdown": {
        "gameweek": 650,
        "monthly": 0
      },
      "highlights": {
        "gameWeeks": 1,
        "gameMonths": 0,
        "overallRank": 34,
        "totalPoints": 804,
        "currentGWPoints": 64,
        "previousRank": 35,
        "deficitFromLeader": 121
      },
      "achievements": {
        "gameweeks": [
          {
            "week": 7,
            "position": "1st",
            "prize": 650,
            "status": "Paid"
          }
        ],
        "months": []
      },
      "positions": {
        "first": 1,
        "second": 0
      },
      "totalPoints": 804,
      "movement": {
        "direction": "up",
        "change": 1,
        "icon": "⬆",
        "displayText": "+1"
      }
    },
    {
      "playerName": "Vikranth Reddy",
      "totalPrizeWon": 500,
      "totalPaid": 0,
      "totalPending": 500,
      "prizeBreakdown": {
        "gameweek": 500,
        "monthly": 0
      },
      "highlights": {
        "gameWeeks": 1,
        "gameMonths": 0,
        "overallRank": 16,
        "totalPoints": 856,
        "currentGWPoints": 71,
        "previousRank": 20,
        "deficitFromLeader": 69
      },
      "achievements": {
        "gameweeks": [
          {
            "week": 15,
            "position": "1st",
            "prize": 500,
            "status": "Pending"
          }
        ],
        "months": []
      },
      "positions": {
        "first": 1,
        "second": 0
      },
      "totalPoints": 856,
      "movement": {
        "direction": "up",
        "change": 4,
        "icon": "⬆",
        "displayText": "+4"
      }
    },
    {
      "playerName": "Varun Gupta",
      "totalPrizeWon": 500,
      "totalPaid": 0,
      "totalPending": 500,
      "prizeBreakdown": {
        "gameweek": 500,
        "monthly": 0
      },
      "highlights": {
        "gameWeeks": 1,
        "gameMonths": 0,
        "overallRank": 12,
        "totalPoints": 866,
        "currentGWPoints": 71,
        "previousRank": 17,
        "deficitFromLeader": 59
      },
      "achievements": {
        "gameweeks": [
          {
            "week": 15,
            "position": "1st",
            "prize": 500,
            "status": "Pending"
          }
        ],
        "months": []
      },
      "positions": {
        "first": 1,
        "second": 0
      },
      "totalPoints": 866,
      "movement": {
        "direction": "up",
        "change": 5,
        "icon": "⬆",
        "displayText": "+5"
      }
    },
    {
      "playerName": "Tejeshwar Singh",
      "totalPrizeWon": 500,
      "totalPaid": 500,
      "totalPending": 0,
      "prizeBreakdown": {
        "gameweek": 500,
        "monthly": 0
      },
      "highlights": {
        "gameWeeks": 1,
        "gameMonths": 0,
        "overallRank": 6,
        "totalPoints": 882,
        "currentGWPoints": 59,
        "previousRank": 10,
        "deficitFromLeader": 43
      },
      "achievements": {
        "gameweeks": [
          {
            "week": 13,
            "position": "1st",
            "prize": 500,
            "status": "Paid"
          }
        ],
        "months": []
      },
      "positions": {
        "first": 1,
        "second": 0
      },
      "totalPoints": 882,
      "movement": {
        "direction": "up",
        "change": 4,
        "icon": "⬆",
        "displayText": "+4"
      }
    },
    {
      "playerName": "Harshit Gupta",
      "totalPrizeWon": 350,
      "totalPaid": 350,
      "totalPending": 0,
      "prizeBreakdown": {
        "gameweek": 350,
        "monthly": 0
      },
      "highlights": {
        "gameWeeks": 1,
        "gameMonths": 0,
        "overallRank": 46,
        "totalPoints": 746,
        "currentGWPoints": 52,
        "previousRank": 49,
        "deficitFromLeader": 179
      },
      "achievements": {
        "gameweeks": [
          {
            "week": 5,
            "position": "2nd",
            "prize": 350,
            "status": "Paid"
          }
        ],
        "months": []
      },
      "positions": {
        "first": 0,
        "second": 1
      },
      "totalPoints": 746,
      "movement": {
        "direction": "up",
        "change": 3,
        "icon": "⬆",
        "displayText": "+3"
      }
    },
    {
      "playerName": "Soman Panda",
      "totalPrizeWon": 350,
      "totalPaid": 350,
      "totalPending": 0,
      "prizeBreakdown": {
        "gameweek": 350,
        "monthly": 0
      },
      "highlights": {
        "gameWeeks": 1,
        "gameMonths": 0,
        "overallRank": 12,
        "totalPoints": 866,
        "currentGWPoints": 68,
        "previousRank": 15,
        "deficitFromLeader": 59
      },
      "achievements": {
        "gameweeks": [
          {
            "week": 7,
            "position": "2nd",
            "prize": 350,
            "status": "Paid"
          }
        ],
        "months": []
      },
      "positions": {
        "first": 0,
        "second": 1
      },
      "totalPoints": 866,
      "movement": {
        "direction": "up",
        "change": 3,
        "icon": "⬆",
        "displayText": "+3"
      }
    },
    {
      "playerName": "Mayur Kriplani",
      "totalPrizeWon": 350,
      "totalPaid": 350,
      "totalPending": 0,
      "prizeBreakdown": {
        "gameweek": 350,
        "monthly": 0
      },
      "highlights": {
        "gameWeeks": 1,
        "gameMonths": 0,
        "overallRank": 24,
        "totalPoints": 831,
        "currentGWPoints": 46,
        "previousRank": 20,
        "deficitFromLeader": 94
      },
      "achievements": {
        "gameweeks": [
          {
            "week": 4,
            "position": "2nd",
            "prize": 350,
            "status": "Paid"
          }
        ],
        "months": []
      },
      "positions": {
        "first": 0,
        "second": 1
      },
      "totalPoints": 831,
      "movement": {
        "direction": "down",
        "change": 4,
        "icon": "⬇",
        "displayText": "-4"
      }
    },
    {
      "playerName": "Ankur Prasad",
      "totalPrizeWon": 350,
      "totalPaid": 350,
      "totalPending": 0,
      "prizeBreakdown": {
        "gameweek": 350,
        "monthly": 0
      },
      "highlights": {
        "gameWeeks": 1,
        "gameMonths": 0,
        "overallRank": 18,
        "totalPoints": 847,
        "currentGWPoints": 66,
        "previousRank": 23,
        "deficitFromLeader": 78
      },
      "achievements": {
        "gameweeks": [
          {
            "week": 11,
            "position": "2nd",
            "prize": 350,
            "status": "Paid"
          }
        ],
        "months": []
      },
      "positions": {
        "first": 0,
        "second": 1
      },
      "totalPoints": 847,
      "movement": {
        "direction": "up",
        "change": 5,
        "icon": "⬆",
        "displayText": "+5"
      }
    },
    {
      "playerName": "Rahul Sahai",
      "totalPrizeWon": 350,
      "totalPaid": 350,
      "totalPending": 0,
      "prizeBreakdown": {
        "gameweek": 350,
        "monthly": 0
      },
      "highlights": {
        "gameWeeks": 1,
        "gameMonths": 0,
        "overallRank": 22,
        "totalPoints": 836,
        "currentGWPoints": 57,
        "previousRank": 24,
        "deficitFromLeader": 89
      },
      "achievements": {
        "gameweeks": [
          {
            "week": 9,
            "position": "2nd",
            "prize": 350,
            "status": "Paid"
          }
        ],
        "months": []
      },
      "positions": {
        "first": 0,
        "second": 1
      },
      "totalPoints": 836,
      "movement": {
        "direction": "up",
        "change": 2,
        "icon": "⬆",
        "displayText": "+2"
      }
    },
    {
      "playerName": "Sanchay Srivastava",
      "totalPrizeWon": 350,
      "totalPaid": 350,
      "totalPending": 0,
      "prizeBreakdown": {
        "gameweek": 350,
        "monthly": 0
      },
      "highlights": {
        "gameWeeks": 1,
        "gameMonths": 0,
        "overallRank": 5,
        "totalPoints": 893,
        "currentGWPoints": 61,
        "previousRank": 6,
        "deficitFromLeader": 32
      },
      "achievements": {
        "gameweeks": [
          {
            "week": 2,
            "position": "2nd",
            "prize": 350,
            "status": "Paid"
          }
        ],
        "months": []
      },
      "positions": {
        "first": 0,
        "second": 1
      },
      "totalPoints": 893,
      "movement": {
        "direction": "up",
        "change": 1,
        "icon": "⬆",
        "displayText": "+1"
      }
    },
    {
      "playerName": "Devesh Singh",
      "totalPrizeWon": 350,
      "totalPaid": 350,
      "totalPending": 0,
      "prizeBreakdown": {
        "gameweek": 350,
        "monthly": 0
      },
      "highlights": {
        "gameWeeks": 1,
        "gameMonths": 0,
        "overallRank": 27,
        "totalPoints": 820,
        "currentGWPoints": 62,
        "previousRank": 31,
        "deficitFromLeader": 105
      },
      "achievements": {
        "gameweeks": [
          {
            "week": 10,
            "position": "2nd",
            "prize": 350,
            "status": "Paid"
          }
        ],
        "months": []
      },
      "positions": {
        "first": 0,
        "second": 1
      },
      "totalPoints": 820,
      "movement": {
        "direction": "up",
        "change": 4,
        "icon": "⬆",
        "displayText": "+4"
      }
    },
    {
      "playerName": "Sivakumar N",
      "totalPrizeWon": 350,
      "totalPaid": 350,
      "totalPending": 0,
      "prizeBreakdown": {
        "gameweek": 350,
        "monthly": 0
      },
      "highlights": {
        "gameWeeks": 1,
        "gameMonths": 0,
        "overallRank": 47,
        "totalPoints": 745,
        "currentGWPoints": 45,
        "previousRank": 47,
        "deficitFromLeader": 180
      },
      "achievements": {
        "gameweeks": [
          {
            "week": 12,
            "position": "2nd",
            "prize": 350,
            "status": "Paid"
          }
        ],
        "months": []
      },
      "positions": {
        "first": 0,
        "second": 1
      },
      "totalPoints": 745,
      "movement": {
        "direction": "same",
        "change": 0,
        "icon": "⚬",
        "displayText": "—"
      }
    },
    {
      "playerName": "Ritesh Motghare",
      "totalPrizeWon": 333,
      "totalPaid": 333,
      "totalPending": 0,
      "prizeBreakdown": {
        "gameweek": 333,
        "monthly": 0
      },
      "highlights": {
        "gameWeeks": 1,
        "gameMonths": 0,
        "overallRank": 23,
        "totalPoints": 834,
        "currentGWPoints": 41,
        "previousRank": 18,
        "deficitFromLeader": 91
      },
      "achievements": {
        "gameweeks": [
          {
            "week": 14,
            "position": "1st",
            "prize": 333,
            "status": "Paid"
          }
        ],
        "months": []
      },
      "positions": {
        "first": 1,
        "second": 0
      },
      "totalPoints": 834,
      "movement": {
        "direction": "down",
        "change": 5,
        "icon": "⬇",
        "displayText": "-5"
      }
    },
    {
      "playerName": "Ashish Kumar",
      "totalPrizeWon": 333,
      "totalPaid": 333,
      "totalPending": 0,
      "prizeBreakdown": {
        "gameweek": 333,
        "monthly": 0
      },
      "highlights": {
        "gameWeeks": 1,
        "gameMonths": 0,
        "overallRank": 37,
        "totalPoints": 785,
        "currentGWPoints": 51,
        "previousRank": 38,
        "deficitFromLeader": 140
      },
      "achievements": {
        "gameweeks": [
          {
            "week": 14,
            "position": "1st",
            "prize": 333,
            "status": "Paid"
          }
        ],
        "months": []
      },
      "positions": {
        "first": 1,
        "second": 0
      },
      "totalPoints": 785,
      "movement": {
        "direction": "up",
        "change": 1,
        "icon": "⬆",
        "displayText": "+1"
      }
    },
    {
      "playerName": "Aditya Garg",
      "totalPrizeWon": 0,
      "totalPaid": 0,
      "totalPending": 0,
      "prizeBreakdown": {
        "gameweek": 0,
        "monthly": 0
      },
      "highlights": {
        "gameWeeks": 0,
        "gameMonths": 0,
        "overallRank": 14,
        "totalPoints": 862,
        "currentGWPoints": 65,
        "previousRank": 16,
        "deficitFromLeader": 63
      },
      "achievements": {
        "gameweeks": [],
        "months": []
      },
      "positions": {
        "first": 0,
        "second": 0
      },
      "totalPoints": 862,
      "movement": {
        "direction": "up",
        "change": 2,
        "icon": "⬆",
        "displayText": "+2"
      }
    },
    {
      "playerName": "Vinod Shankar",
      "totalPrizeWon": 0,
      "totalPaid": 0,
      "totalPending": 0,
      "prizeBreakdown": {
        "gameweek": 0,
        "monthly": 0
      },
      "highlights": {
        "gameWeeks": 0,
        "gameMonths": 0,
        "overallRank": 7,
        "totalPoints": 878,
        "currentGWPoints": 47,
        "previousRank": 7,
        "deficitFromLeader": 47
      },
      "achievements": {
        "gameweeks": [],
        "months": []
      },
      "positions": {
        "first": 0,
        "second": 0
      },
      "totalPoints": 878,
      "movement": {
        "direction": "same",
        "change": 0,
        "icon": "⚬",
        "displayText": "—"
      }
    },
    {
      "playerName": "Anish Banerjee",
      "totalPrizeWon": 0,
      "totalPaid": 0,
      "totalPending": 0,
      "prizeBreakdown": {
        "gameweek": 0,
        "monthly": 0
      },
      "highlights": {
        "gameWeeks": 0,
        "gameMonths": 0,
        "overallRank": 15,
        "totalPoints": 858,
        "currentGWPoints": 42,
        "previousRank": 12,
        "deficitFromLeader": 67
      },
      "achievements": {
        "gameweeks": [],
        "months": []
      },
      "positions": {
        "first": 0,
        "second": 0
      },
      "totalPoints": 858,
      "movement": {
        "direction": "down",
        "change": 3,
        "icon": "⬇",
        "displayText": "-3"
      }
    },
    {
      "playerName": "Rohan Desai",
      "totalPrizeWon": 0,
      "totalPaid": 0,
      "totalPending": 0,
      "prizeBreakdown": {
        "gameweek": 0,
        "monthly": 0
      },
      "highlights": {
        "gameWeeks": 0,
        "gameMonths": 0,
        "overallRank": 35,
        "totalPoints": 803,
        "currentGWPoints": 64,
        "previousRank": 36,
        "deficitFromLeader": 122
      },
      "achievements": {
        "gameweeks": [],
        "months": []
      },
      "positions": {
        "first": 0,
        "second": 0
      },
      "totalPoints": 803,
      "movement": {
        "direction": "up",
        "change": 1,
        "icon": "⬆",
        "displayText": "+1"
      }
    },
    {
      "playerName": "Somnath Pawar ",
      "totalPrizeWon": 0,
      "totalPaid": 0,
      "totalPending": 0,
      "prizeBreakdown": {
        "gameweek": 0,
        "monthly": 0
      },
      "highlights": {
        "gameWeeks": 0,
        "gameMonths": 0,
        "overallRank": 41,
        "totalPoints": 771,
        "currentGWPoints": 63,
        "previousRank": 44,
        "deficitFromLeader": 154
      },
      "achievements": {
        "gameweeks": [],
        "months": []
      },
      "positions": {
        "first": 0,
        "second": 0
      },
      "totalPoints": 771,
      "movement": {
        "direction": "up",
        "change": 3,
        "icon": "⬆",
        "displayText": "+3"
      }
    },
    {
      "playerName": "Pallab Pegu",
      "totalPrizeWon": 0,
      "totalPaid": 0,
      "totalPending": 0,
      "prizeBreakdown": {
        "gameweek": 0,
        "monthly": 0
      },
      "highlights": {
        "gameWeeks": 0,
        "gameMonths": 0,
        "overallRank": 42,
        "totalPoints": 768,
        "currentGWPoints": 56,
        "previousRank": 43,
        "deficitFromLeader": 157
      },
      "achievements": {
        "gameweeks": [],
        "months": []
      },
      "positions": {
        "first": 0,
        "second": 0
      },
      "totalPoints": 768,
      "movement": {
        "direction": "up",
        "change": 1,
        "icon": "⬆",
        "displayText": "+1"
      }
    },
    {
      "playerName": "Sushil Coppa",
      "totalPrizeWon": 0,
      "totalPaid": 0,
      "totalPending": 0,
      "prizeBreakdown": {
        "gameweek": 0,
        "monthly": 0
      },
      "highlights": {
        "gameWeeks": 0,
        "gameMonths": 0,
        "overallRank": 52,
        "totalPoints": 691,
        "currentGWPoints": 46,
        "previousRank": 51,
        "deficitFromLeader": 234
      },
      "achievements": {
        "gameweeks": [],
        "months": []
      },
      "positions": {
        "first": 0,
        "second": 0
      },
      "totalPoints": 691,
      "movement": {
        "direction": "down",
        "change": 1,
        "icon": "⬇",
        "displayText": "-1"
      }
    },
    {
      "playerName": "Bharanidharan S",
      "totalPrizeWon": 0,
      "totalPaid": 0,
      "totalPending": 0,
      "prizeBreakdown": {
        "gameweek": 0,
        "monthly": 0
      },
      "highlights": {
        "gameWeeks": 0,
        "gameMonths": 0,
        "overallRank": 33,
        "totalPoints": 807,
        "currentGWPoints": 48,
        "previousRank": 30,
        "deficitFromLeader": 118
      },
      "achievements": {
        "gameweeks": [],
        "months": []
      },
      "positions": {
        "first": 0,
        "second": 0
      },
      "totalPoints": 807,
      "movement": {
        "direction": "down",
        "change": 3,
        "icon": "⬇",
        "displayText": "-3"
      }
    },
    {
      "playerName": "Ronak Kadikar",
      "totalPrizeWon": 0,
      "totalPaid": 0,
      "totalPending": 0,
      "prizeBreakdown": {
        "gameweek": 0,
        "monthly": 0
      },
      "highlights": {
        "gameWeeks": 0,
        "gameMonths": 0,
        "overallRank": 51,
        "totalPoints": 699,
        "currentGWPoints": 57,
        "previousRank": 52,
        "deficitFromLeader": 226
      },
      "achievements": {
        "gameweeks": [],
        "months": []
      },
      "positions": {
        "first": 0,
        "second": 0
      },
      "totalPoints": 699,
      "movement": {
        "direction": "up",
        "change": 1,
        "icon": "⬆",
        "displayText": "+1"
      }
    },
    {
      "playerName": "Kashyap Rana",
      "totalPrizeWon": 0,
      "totalPaid": 0,
      "totalPending": 0,
      "prizeBreakdown": {
        "gameweek": 0,
        "monthly": 0
      },
      "highlights": {
        "gameWeeks": 0,
        "gameMonths": 0,
        "overallRank": 29,
        "totalPoints": 816,
        "currentGWPoints": 52,
        "previousRank": 29,
        "deficitFromLeader": 109
      },
      "achievements": {
        "gameweeks": [],
        "months": []
      },
      "positions": {
        "first": 0,
        "second": 0
      },
      "totalPoints": 816,
      "movement": {
        "direction": "same",
        "change": 0,
        "icon": "⚬",
        "displayText": "—"
      }
    },
    {
      "playerName": "Abhishek Ghorpade",
      "totalPrizeWon": 0,
      "totalPaid": 0,
      "totalPending": 0,
      "prizeBreakdown": {
        "gameweek": 0,
        "monthly": 0
      },
      "highlights": {
        "gameWeeks": 0,
        "gameMonths": 0,
        "overallRank": 45,
        "totalPoints": 748,
        "currentGWPoints": 47,
        "previousRank": 45,
        "deficitFromLeader": 177
      },
      "achievements": {
        "gameweeks": [],
        "months": []
      },
      "positions": {
        "first": 0,
        "second": 0
      },
      "totalPoints": 748,
      "movement": {
        "direction": "same",
        "change": 0,
        "icon": "⚬",
        "displayText": "—"
      }
    },
    {
      "playerName": "Varun Elango",
      "totalPrizeWon": 0,
      "totalPaid": 0,
      "totalPending": 0,
      "prizeBreakdown": {
        "gameweek": 0,
        "monthly": 0
      },
      "highlights": {
        "gameWeeks": 0,
        "gameMonths": 0,
        "overallRank": 11,
        "totalPoints": 870,
        "currentGWPoints": 59,
        "previousRank": 13,
        "deficitFromLeader": 55
      },
      "achievements": {
        "gameweeks": [],
        "months": []
      },
      "positions": {
        "first": 0,
        "second": 0
      },
      "totalPoints": 870,
      "movement": {
        "direction": "up",
        "change": 2,
        "icon": "⬆",
        "displayText": "+2"
      }
    },
    {
      "playerName": "Soubhik Chakraborty ",
      "totalPrizeWon": 0,
      "totalPaid": 0,
      "totalPending": 0,
      "prizeBreakdown": {
        "gameweek": 0,
        "monthly": 0
      },
      "highlights": {
        "gameWeeks": 0,
        "gameMonths": 0,
        "overallRank": 28,
        "totalPoints": 817,
        "currentGWPoints": 50,
        "previousRank": 27,
        "deficitFromLeader": 108
      },
      "achievements": {
        "gameweeks": [],
        "months": []
      },
      "positions": {
        "first": 0,
        "second": 0
      },
      "totalPoints": 817,
      "movement": {
        "direction": "down",
        "change": 1,
        "icon": "⬇",
        "displayText": "-1"
      }
    },
    {
      "playerName": "Avinash Jayashankar ",
      "totalPrizeWon": 0,
      "totalPaid": 0,
      "totalPending": 0,
      "prizeBreakdown": {
        "gameweek": 0,
        "monthly": 0
      },
      "highlights": {
        "gameWeeks": 0,
        "gameMonths": 0,
        "overallRank": 21,
        "totalPoints": 840,
        "currentGWPoints": 62,
        "previousRank": 26,
        "deficitFromLeader": 85
      },
      "achievements": {
        "gameweeks": [],
        "months": []
      },
      "positions": {
        "first": 0,
        "second": 0
      },
      "totalPoints": 840,
      "movement": {
        "direction": "up",
        "change": 5,
        "icon": "⬆",
        "displayText": "+5"
      }
    },
    {
      "playerName": "Shivam Sachan",
      "totalPrizeWon": 0,
      "totalPaid": 0,
      "totalPending": 0,
      "prizeBreakdown": {
        "gameweek": 0,
        "monthly": 0
      },
      "highlights": {
        "gameWeeks": 0,
        "gameMonths": 0,
        "overallRank": 54,
        "totalPoints": 606,
        "currentGWPoints": 67,
        "previousRank": 54,
        "deficitFromLeader": 319
      },
      "achievements": {
        "gameweeks": [],
        "months": []
      },
      "positions": {
        "first": 0,
        "second": 0
      },
      "totalPoints": 606,
      "movement": {
        "direction": "same",
        "change": 0,
        "icon": "⚬",
        "displayText": "—"
      }
    },
    {
      "playerName": "Vikash Kumar",
      "totalPrizeWon": 0,
      "totalPaid": 0,
      "totalPending": 0,
      "prizeBreakdown": {
        "gameweek": 0,
        "monthly": 0
      },
      "highlights": {
        "gameWeeks": 0,
        "gameMonths": 0,
        "overallRank": 17,
        "totalPoints": 853,
        "currentGWPoints": 35,
        "previousRank": 11,
        "deficitFromLeader": 72
      },
      "achievements": {
        "gameweeks": [],
        "months": []
      },
      "positions": {
        "first": 0,
        "second": 0
      },
      "totalPoints": 853,
      "movement": {
        "direction": "down",
        "change": 6,
        "icon": "⬇",
        "displayText": "-6"
      }
    },
    {
      "playerName": "Ansh Makhija",
      "totalPrizeWon": 0,
      "totalPaid": 0,
      "totalPending": 0,
      "prizeBreakdown": {
        "gameweek": 0,
        "monthly": 0
      },
      "highlights": {
        "gameWeeks": 0,
        "gameMonths": 0,
        "overallRank": 40,
        "totalPoints": 775,
        "currentGWPoints": 37,
        "previousRank": 37,
        "deficitFromLeader": 150
      },
      "achievements": {
        "gameweeks": [],
        "months": []
      },
      "positions": {
        "first": 0,
        "second": 0
      },
      "totalPoints": 775,
      "movement": {
        "direction": "down",
        "change": 3,
        "icon": "⬇",
        "displayText": "-3"
      }
    },
    {
      "playerName": "Abhishek Addy",
      "totalPrizeWon": 0,
      "totalPaid": 0,
      "totalPending": 0,
      "prizeBreakdown": {
        "gameweek": 0,
        "monthly": 0
      },
      "highlights": {
        "gameWeeks": 0,
        "gameMonths": 0,
        "overallRank": 48,
        "totalPoints": 743,
        "currentGWPoints": 47,
        "previousRank": 48,
        "deficitFromLeader": 182
      },
      "achievements": {
        "gameweeks": [],
        "months": []
      },
      "positions": {
        "first": 0,
        "second": 0
      },
      "totalPoints": 743,
      "movement": {
        "direction": "same",
        "change": 0,
        "icon": "⚬",
        "displayText": "—"
      }
    },
    {
      "playerName": "Harshvardhan Maru",
      "totalPrizeWon": 0,
      "totalPaid": 0,
      "totalPending": 0,
      "prizeBreakdown": {
        "gameweek": 0,
        "monthly": 0
      },
      "highlights": {
        "gameWeeks": 0,
        "gameMonths": 0,
        "overallRank": 25,
        "totalPoints": 829,
        "currentGWPoints": 50,
        "previousRank": 24,
        "deficitFromLeader": 96
      },
      "achievements": {
        "gameweeks": [],
        "months": []
      },
      "positions": {
        "first": 0,
        "second": 0
      },
      "totalPoints": 829,
      "movement": {
        "direction": "down",
        "change": 1,
        "icon": "⬇",
        "displayText": "-1"
      }
    },
    {
      "playerName": "Ashutosh Thombal",
      "totalPrizeWon": 0,
      "totalPaid": 0,
      "totalPending": 0,
      "prizeBreakdown": {
        "gameweek": 0,
        "monthly": 0
      },
      "highlights": {
        "gameWeeks": 0,
        "gameMonths": 0,
        "overallRank": 26,
        "totalPoints": 827,
        "currentGWPoints": 44,
        "previousRank": 22,
        "deficitFromLeader": 98
      },
      "achievements": {
        "gameweeks": [],
        "months": []
      },
      "positions": {
        "first": 0,
        "second": 0
      },
      "totalPoints": 827,
      "movement": {
        "direction": "down",
        "change": 4,
        "icon": "⬇",
        "displayText": "-4"
      }
    },
    {
      "playerName": "Praveen Pujer",
      "totalPrizeWon": 0,
      "totalPaid": 0,
      "totalPending": 0,
      "prizeBreakdown": {
        "gameweek": 0,
        "monthly": 0
      },
      "highlights": {
        "gameWeeks": 0,
        "gameMonths": 0,
        "overallRank": 44,
        "totalPoints": 758,
        "currentGWPoints": 37,
        "previousRank": 40,
        "deficitFromLeader": 167
      },
      "achievements": {
        "gameweeks": [],
        "months": []
      },
      "positions": {
        "first": 0,
        "second": 0
      },
      "totalPoints": 758,
      "movement": {
        "direction": "down",
        "change": 4,
        "icon": "⬇",
        "displayText": "-4"
      }
    },
    {
      "playerName": "Gaurav G B",
      "totalPrizeWon": 0,
      "totalPaid": 0,
      "totalPending": 0,
      "prizeBreakdown": {
        "gameweek": 0,
        "monthly": 0
      },
      "highlights": {
        "gameWeeks": 0,
        "gameMonths": 0,
        "overallRank": 48,
        "totalPoints": 743,
        "currentGWPoints": 42,
        "previousRank": 45,
        "deficitFromLeader": 182
      },
      "achievements": {
        "gameweeks": [],
        "months": []
      },
      "positions": {
        "first": 0,
        "second": 0
      },
      "totalPoints": 743,
      "movement": {
        "direction": "down",
        "change": 3,
        "icon": "⬇",
        "displayText": "-3"
      }
    },
    {
      "playerName": "Parth Pillai",
      "totalPrizeWon": 0,
      "totalPaid": 0,
      "totalPending": 0,
      "prizeBreakdown": {
        "gameweek": 0,
        "monthly": 0
      },
      "highlights": {
        "gameWeeks": 0,
        "gameMonths": 0,
        "overallRank": 43,
        "totalPoints": 766,
        "currentGWPoints": 49,
        "previousRank": 41,
        "deficitFromLeader": 159
      },
      "achievements": {
        "gameweeks": [],
        "months": []
      },
      "positions": {
        "first": 0,
        "second": 0
      },
      "totalPoints": 766,
      "movement": {
        "direction": "down",
        "change": 2,
        "icon": "⬇",
        "displayText": "-2"
      }
    },
    {
      "playerName": "Maheep Ajay",
      "totalPrizeWon": 0,
      "totalPaid": 0,
      "totalPending": 0,
      "prizeBreakdown": {
        "gameweek": 0,
        "monthly": 0
      },
      "highlights": {
        "gameWeeks": 0,
        "gameMonths": 0,
        "overallRank": 39,
        "totalPoints": 778,
        "currentGWPoints": 61,
        "previousRank": 41,
        "deficitFromLeader": 147
      },
      "achievements": {
        "gameweeks": [],
        "months": []
      },
      "positions": {
        "first": 0,
        "second": 0
      },
      "totalPoints": 778,
      "movement": {
        "direction": "up",
        "change": 2,
        "icon": "⬆",
        "displayText": "+2"
      }
    },
    {
      "playerName": "Nipun Kochar",
      "totalPrizeWon": 0,
      "totalPaid": 0,
      "totalPending": 0,
      "prizeBreakdown": {
        "gameweek": 0,
        "monthly": 0
      },
      "highlights": {
        "gameWeeks": 0,
        "gameMonths": 0,
        "overallRank": 38,
        "totalPoints": 781,
        "currentGWPoints": 59,
        "previousRank": 39,
        "deficitFromLeader": 144
      },
      "achievements": {
        "gameweeks": [],
        "months": []
      },
      "positions": {
        "first": 0,
        "second": 0
      },
      "totalPoints": 781,
      "movement": {
        "direction": "up",
        "change": 1,
        "icon": "⬆",
        "displayText": "+1"
      }
    },
    {
      "playerName": "Abhishek Agarwal",
      "totalPrizeWon": 0,
      "totalPaid": 0,
      "totalPending": 0,
      "prizeBreakdown": {
        "gameweek": 0,
        "monthly": 0
      },
      "highlights": {
        "gameWeeks": 0,
        "gameMonths": 0,
        "overallRank": 30,
        "totalPoints": 815,
        "currentGWPoints": 48,
        "previousRank": 27,
        "deficitFromLeader": 110
      },
      "achievements": {
        "gameweeks": [],
        "months": []
      },
      "positions": {
        "first": 0,
        "second": 0
      },
      "totalPoints": 815,
      "movement": {
        "direction": "down",
        "change": 3,
        "icon": "⬇",
        "displayText": "-3"
      }
    }
  ],
  "enhancements": {
    "leaderboardEnhanced": true,
    "enhancementVersion": "1.0.0",
    "enhancedAt": "2025-12-09T07:24:34.603Z",
    "enhancementFeatures": [
      "previousRank",
      "currentGWPoints",
      "deficitFromLeader",
      "movementIndicators"
    ]
  }
}